cdk_opinionated_constructs/__init__.py
cdk_opinionated_constructs/alb.py
cdk_opinionated_constructs/ecr.py
cdk_opinionated_constructs/lmb.py
cdk_opinionated_constructs/nlb.py
cdk_opinionated_constructs/rds_instance.py
cdk_opinionated_constructs/s3.py
cdk_opinionated_constructs/sns.py
cdk_opinionated_constructs/wafv2.py
cdk_opinionated_constructs/libs/__init__.py
cdk_opinionated_constructs/libs/pipeline_v2/__init__.py
cdk_opinionated_constructs/libs/pipeline_v2/aws_lambda.py
cdk_opinionated_constructs/libs/pipeline_v2/docker.py
cdk_opinionated_constructs/libs/pipeline_v2/oci_image_validation.py
cdk_opinionated_constructs/libs/pipeline_v2/oci_signer.py
cdk_opinionated_constructs/libs/pipeline_v2/soci_index.py
cdk_opinionated_constructs/libs/pipeline_v2/trivy_scaner.py
cdk_opinionated_constructs/schemas/__init__.py
cdk_opinionated_constructs/schemas/configuration_vars.py
cdk_opinionated_constructs/stacks/__init__.py
cdk_opinionated_constructs/stacks/code_quality_stack.py
cdk_opinionated_constructs/stacks/governance_stack.py
cdk_opinionated_constructs/stacks/infrastructure_tests_stack.py
cdk_opinionated_constructs/stacks/integration_tests_stack.py
cdk_opinionated_constructs/stacks/notifications_stack.py
cdk_opinionated_constructs/stacks/pipeline_plugins_stack.py
cdk_opinionated_constructs/stacks/pipeline_trigger_stack.py
cdk_opinionated_constructs/stacks/services_tests_stack.py
cdk_opinionated_constructs/stages/__init__.py
cdk_opinionated_constructs/stages/code_quality_stage.py
cdk_opinionated_constructs/stages/infrastructure_tests_stage.py
cdk_opinionated_constructs/stages/integration_tests_stage.py
cdk_opinionated_constructs/stages/notifications_stage.py
cdk_opinionated_constructs/stages/plugins_stage.py
cdk_opinionated_constructs/stages/services_tests_stage.py
cdk_opinionated_constructs/stages/logic/__init__.py
cdk_opinionated_constructs/utils/__init__.py
cdk_opinionated_constructs/utils/trivy_docker_image_security_hub_parser.py
cdk_opinionated_constructs-4.7.34.dist-info/licenses/LICENSE
cdk_opinionated_constructs-4.7.34.dist-info/METADATA
cdk_opinionated_constructs-4.7.34.dist-info/WHEEL
cdk_opinionated_constructs-4.7.34.dist-info/top_level.txt
cdk_opinionated_constructs-4.7.34.dist-info/RECORD
