Metadata-Version: 2.4
Name: cdk-opinionated-constructs
Version: 4.7.34
Summary: AWS CDK constructs come without added security configurations.
License: MIT
Requires-Python: >=3.11
License-File: LICENSE
Requires-Dist: aws-cdk-lib>=2.177.0
Requires-Dist: constructs>=10.4.2
Requires-Dist: cdk-monitoring-constructs>=6.0.0
Requires-Dist: pydantic>=2.9.0
Requires-Dist: pydantic-core>=2.23.0
Requires-Dist: pyyaml>=6.0.0
Requires-Dist: tenacity>=8.0.1
Requires-Dist: click>=8.1.3
Requires-Dist: typeguard~=2.13.3
Dynamic: description
Dynamic: license
Dynamic: license-file
Dynamic: requires-dist
Dynamic: requires-python
Dynamic: summary
